<?xml version="1.0"?>
<config>
	<menu>
		<catalog>
			<children>
				<testalbum translate="title" module="tungtt_magefinal">
					<title>Album Manager</title>
					<sort_order>1</sort_order>
					<action>adminhtml/album</action>
				</testalbum>
			</children>
		</catalog>
	</menu>
	<acl>
		<resources>
			<admin>
				<children>
					<catalog>
						<children>
							<testalbum translate="title" module="tungtt_magefinal">
								<title>Album Manager</title>
								<sort_order>1</sort_order>
							</testalbum>
						</children>
					</catalog>
				</children>
			</admin>
		</resources>
	</acl>
</config>